Segmentfault2015YouxiuWenzhang/README.md
Segmentfault2015YouxiuWenzhang/__init__.py
Segmentfault2015YouxiuWenzhang/__main__.py
Segmentfault2015YouxiuWenzhang/file.epub
Segmentfault2015YouxiuWenzhang/index.html
Segmentfault2015YouxiuWenzhang/css/__init__.py
Segmentfault2015YouxiuWenzhang/css/annotations.css
Segmentfault2015YouxiuWenzhang/css/main.css
Segmentfault2015YouxiuWenzhang/css/normalize.css
Segmentfault2015YouxiuWenzhang/css/popup.css
Segmentfault2015YouxiuWenzhang/font/__init__.py
Segmentfault2015YouxiuWenzhang/font/fontello.eot
Segmentfault2015YouxiuWenzhang/font/fontello.svg
Segmentfault2015YouxiuWenzhang/font/fontello.ttf
Segmentfault2015YouxiuWenzhang/font/fontello.woff
Segmentfault2015YouxiuWenzhang/img/__init__.py
Segmentfault2015YouxiuWenzhang/img/annotator-glyph-sprite.png
Segmentfault2015YouxiuWenzhang/img/annotator-icon-sprite.png
Segmentfault2015YouxiuWenzhang/img/apple-touch-icon.png
Segmentfault2015YouxiuWenzhang/img/cancelfullscreen.png
Segmentfault2015YouxiuWenzhang/img/close.png
Segmentfault2015YouxiuWenzhang/img/fullscreen.png
Segmentfault2015YouxiuWenzhang/img/loader.gif
Segmentfault2015YouxiuWenzhang/img/menu-icon.png
Segmentfault2015YouxiuWenzhang/img/save.png
Segmentfault2015YouxiuWenzhang/img/saved.png
Segmentfault2015YouxiuWenzhang/img/settings-s.png
Segmentfault2015YouxiuWenzhang/img/settings.png
Segmentfault2015YouxiuWenzhang/img/star.png
Segmentfault2015YouxiuWenzhang/js/__init__.py
Segmentfault2015YouxiuWenzhang/js/epub.js
Segmentfault2015YouxiuWenzhang/js/epub.min.js
Segmentfault2015YouxiuWenzhang/js/epub.min.map
Segmentfault2015YouxiuWenzhang/js/hooks.min.js
Segmentfault2015YouxiuWenzhang/js/hooks.min.map
Segmentfault2015YouxiuWenzhang/js/reader.js
Segmentfault2015YouxiuWenzhang/js/reader.js.map
Segmentfault2015YouxiuWenzhang/js/reader.min.js
Segmentfault2015YouxiuWenzhang/js/reader.min.map
Segmentfault2015YouxiuWenzhang/js/hooks/__init__.py
Segmentfault2015YouxiuWenzhang/js/hooks/extensions/__init__.py
segmentfault_2015_youxiu_wenzhang-2024.3.1.0.dist-info/METADATA
segmentfault_2015_youxiu_wenzhang-2024.3.1.0.dist-info/WHEEL
segmentfault_2015_youxiu_wenzhang-2024.3.1.0.dist-info/entry_points.txt
segmentfault_2015_youxiu_wenzhang-2024.3.1.0.dist-info/top_level.txt
segmentfault_2015_youxiu_wenzhang-2024.3.1.0.dist-info/RECORD
